griblet/__init__.py
griblet/computation_graph.py
griblet/computation_tree.py
griblet/dependency_solver.py
griblet/loader_and_cache.py
griblet/tree_evaluator.py
griblet-0.1.0.dist-info/licenses/LICENSE.md
griblet-0.1.0.dist-info/METADATA
griblet-0.1.0.dist-info/WHEEL
griblet-0.1.0.dist-info/top_level.txt
griblet-0.1.0.dist-info/RECORD
