Metadata-Version: 2.4
Name: griblet
Version: 0.1.0
Summary: Distill the optimal computation tree from a field of possibilities.
Author-email: Dag Evensberget <dag.evensberget@gmail.com>
Project-URL: Homepage, https://github.com/svaberg/griblet
Project-URL: Repository, https://github.com/svaberg/griblet
Project-URL: Issues, https://github.com/svaberg/griblet/issues
Requires-Python: >=3.8
License-File: LICENSE.md
Requires-Dist: numpy
Requires-Dist: astropy
Dynamic: license-file
